rlgym_trueskill/__init__.py
rlgym_trueskill/trueskillworkers.py
rlgym_trueskill-0.1.0.dist-info/licenses/LICENSE
rlgym_trueskill-0.1.0.dist-info/METADATA
rlgym_trueskill-0.1.0.dist-info/WHEEL
rlgym_trueskill-0.1.0.dist-info/top_level.txt
rlgym_trueskill-0.1.0.dist-info/RECORD
