Metadata-Version: 2.4
Name: rlgym-trueskill
Version: 0.1.0
Summary: A Python package for TrueSkill-based ranking in RLGym environments
Author: chrisrca, ericle85
License: Copyright 2025 chrisrca
Project-URL: Repository, https://github.com/chrisrca/rlgym-trueskill
Keywords: rlgym,trueskill,rocket-league,ranking
Classifier: Programming Language :: Python :: 3.9
Classifier: License :: OSI Approved :: MIT License
Classifier: Operating System :: OS Independent
Requires-Python: ==3.9.*
License-File: LICENSE
Requires-Dist: rlgym==2.0.1
Requires-Dist: trueskill==0.4.5
Requires-Dist: setuptools
Requires-Dist: wheel
Requires-Dist: build
Requires-Dist: twine
Requires-Dist: pytest
Dynamic: license-file
